lain_upload/__init__.py
lain_upload/__main__.py
lain_upload/cli.py
lain_upload/progress.py
lain_upload/upload.py
lain_upload/version.py
lain_upload-1.16.dist-info/licenses/LICENSE
lain_upload-1.16.dist-info/WHEEL
lain_upload-1.16.dist-info/entry_points.txt
lain_upload-1.16.dist-info/METADATA
lain_upload-1.16.dist-info/RECORD
